msscrawler/__init__.py
msscrawler/base_crawler.py
msscrawler/generic_crawler.py
msscrawler/connectors/__init__.py
msscrawler/connectors/databases/__init__.py
msscrawler/connectors/databases/base.py
msscrawler/connectors/databases/mongodb_connector.py
msscrawler/connectors/message_brokers/__init__.py
msscrawler/connectors/message_brokers/base.py
msscrawler/connectors/message_brokers/rabbitmq_connector.py
msscrawler/items/__init__.py
msscrawler/items/base.py
msscrawler/items/brand_item.py
msscrawler/items/category_item.py
msscrawler/items/product_item.py
msscrawler/items/website_item.py
msscrawler/log/__init__.py
msscrawler/log/default.py
msscrawler/middlewares/__init__.py
msscrawler/mixins/__init__.py
msscrawler/mixins/database_mixin.py
msscrawler/mixins/env_loader_mixin.py
msscrawler/mixins/message_connector_mixin.py
msscrawler/mixins/spider_cache_mixin.py
msscrawler/pipelines/__init__.py
msscrawler/pipelines/base.py
msscrawler/sites/__init__.py
msscrawler/sites/shopping/__init__.py
msscrawler/sites/shopping/website_crawler.py
msscrawler/sites/shopping/website_item.py
msscrawler/sites/shopping/website_pipeline.py
msscrawler/sites/shopping/spiders/__init__.py
msscrawler/sites/shopping/spiders/website_theamall_spider.py
msscrawler/spiders/__init__.py
msscrawler/spiders/base.py
msscrawler/spiders/brand.py
msscrawler/spiders/category.py
msscrawler/spiders/product.py
msscrawler/spiders/website.py
msscrawler-1.3.7.dist-info/METADATA
msscrawler-1.3.7.dist-info/WHEEL
msscrawler-1.3.7.dist-info/top_level.txt
msscrawler-1.3.7.dist-info/RECORD
