Metadata-Version: 2.1
Name: msscrawler
Version: 1.3.7
Summary: A common package for crawling
Home-page: https://bitbucket.org/dosiin/common/src/package/
Author: no name
Author-email: msscrawler@gmail.com
Project-URL: Bug Tracker, https://bitbucket.org/dosiin/common/src/package/issues
Project-URL: repository, https://bitbucket.org/dosiin/common/src/package/
Classifier: Programming Language :: Python :: 3
Classifier: License :: OSI Approved :: MIT License
Classifier: Operating System :: OS Independent
Requires-Python: >=3.10
